odoo/addons/dms_file_api/CHANGELOG.md
odoo/addons/dms_file_api/README.rst
odoo/addons/dms_file_api/__init__.py
odoo/addons/dms_file_api/__manifest__.py
odoo/addons/dms_file_api/controllers/__init__.py
odoo/addons/dms_file_api/controllers/main.py
odoo/addons/dms_file_api/demo/dms_category.xml
odoo/addons/dms_file_api/i18n/ca_ES.po
odoo/addons/dms_file_api/i18n/es.po
odoo/addons/dms_file_api/models/__init__.py
odoo/addons/dms_file_api/models/category.py
odoo/addons/dms_file_api/services/__init__.py
odoo/addons/dms_file_api/services/dms_file_service.py
odoo/addons/dms_file_api/services/schemas.py
odoo/addons/dms_file_api/static/description/icon.png
odoo/addons/dms_file_api/tests/__init__.py
odoo/addons/dms_file_api/tests/models/test_dms_category.py
odoo/addons/dms_file_api/tests/services/__init__.py
odoo/addons/dms_file_api/tests/services/test_dms_file_service.py
odoo/addons/dms_file_api/views/dms_category.xml
odoo12_addon_dms_file_api-12.0.0.1.0.dist-info/METADATA
odoo12_addon_dms_file_api-12.0.0.1.0.dist-info/WHEEL
odoo12_addon_dms_file_api-12.0.0.1.0.dist-info/top_level.txt
odoo12_addon_dms_file_api-12.0.0.1.0.dist-info/RECORD
