Metadata-Version: 2.1
Name: odoo12-addon-dms-file-api
Version: 12.0.0.1.0
Summary: Expose an API-Key authenticated API to get and create dms files.
Home-page: https://gitlab.com/somitcoop/erp-research/odoo-helpdesk
Author: Som It Cooperatiu SCCL, Som Connexió SCCL,
License: AGPL-3
Platform: UNKNOWN
Classifier: Programming Language :: Python
Classifier: Framework :: Odoo
Classifier: Framework :: Odoo :: 12.0
Classifier: License :: OSI Approved :: GNU Affero General Public License v3
Requires-Python: >=3.5
Requires-Dist: odoo12-addon-api-common-base
Requires-Dist: odoo12-addon-dms-res-model-root-directory
Requires-Dist: odoo <12.1dev,>=12.0a
